CID-SD232/compare.v
`timescale 1 ns / 1 ps

module compare(
    input clk_dest,
    input rst_n,
    input       [3:0] count,
    output reg  [3:0] even_count
);

always @(posedge clk_dest or negedge rst_n) begin
    
	if (!rst_n) begin
		even_count <= 4'b0;
	end else
		if (count[0] == 0) even_count <= even_count + 1;
	end

endmodule

CID-SD232/cdc.v
`timescale 1 ns / 1 ps

module cdc (
    input clk_src,       
    input clk_dest,      
    input rst_n,
    input [3:0] count,   
    output [3:0] sync_out 
);

    reg [3:0] q_src; 
    reg [3:0] q1, q2; 

    always @(posedge clk_src or negedge rst_n) begin
        if (!rst_n) begin
            q_src <= 4'b0;
        end else begin
            q_src <= count;
        end
    end

    always @(posedge clk_dest or negedge rst_n) begin
        if (!rst_n) begin
            q1       <= 4'b0;
            q2       <= 4'b0;
        end else begin
            q1       <= q_src; 
            q2       <= q1;    
        end
    end
    
    assign sync_out = rst_n ? q2 : 4'b0;

endmodule

CID-ADVANCED/CID-SD232/contador_sincrono.v
`timescale 1 ns / 1 ps

module contador_sincrono (
    input clk_src,                       
    input rst_n,                                            
    output reg [3:0] count               
);

    always @(posedge clk_src or negedge rst_n) begin
        if (!rst_n) begin
            count <= 4'b0;
        end else begin
            if (count >= 4'b1111) begin
                count <= 4'b0;        // Retorna a zero ao atingir o máximo
            end else begin
                count <= count + 1'b1;     // Incrementa a contagem
            end
        end
    end

endmodule

CID-ADVANCED/CID-SD232/top.v
`include "contador_sincrono.v"
`include "cdc.v"
`include "compare.v"

`timescale 1 ns / 1 ps

module top (
    
    input clk_dest, clk_src,
    input rst_n,
    output  [3:0] data_out
    
);
	wire [3:0] count_cdc_in, count_cdc_out;

	contador_sincrono COUNTER_SYNC_module (  
		.clk_src(clk_src),
		.rst_n (rst_n),
		.count (count_cdc_in)
	);

	cdc CDC_module (   
		.clk_dest(clk_dest),
		.clk_src (clk_src),
		.rst_n(rst_n),
		.count(count_cdc_in),
		.sync_out(count_cdc_out)
	);

	compare COMPARE_module ( 
		.clk_dest(clk_dest),
		.rst_n (rst_n),
		.count(count_cdc_out),
		.even_count(data_out)
	);

endmodule

CID-SD232/top_packet_loss_tb.v
`include "top.v"

`timescale 1 ns / 1 ps

module CDC_module_packet_loss_tb;

    // Sinais de interface
    reg clk_src;
    reg clk_dest;
    reg rst_n;
    wire [3:0] data_out;

    // Instanciação do circuito sob teste (DUT)
    top dut (
        .clk_dest(clk_dest),
        .clk_src(clk_src),
        .rst_n(rst_n),
        .data_out(data_out)
    );

    // CONFIGURAÇÃO DOS CLOCKS (Cenário de Perda de Amostras)
    // clk_src muito rápido (Período = 10ns -> 100MHz)  
	always #5 clk_src = ~clk_src;

    // clk_dest muito lento (Período = 35ns -> ~28.5MHz)
    	always #17.5 clk_dest = ~clk_dest;

	initial begin
		$dumpfile("dump_fail.vcd");
		$dumpvars(0, CDC_module_packet_loss_tb);
	end
	
    // GERAÇÃO DE ESTÍMULOS
    initial begin
    
        $display("[TB] Iniciando simulacao de CDC_module com perda de pacotes (Verilog)...");
        
        clk_src = 1'b0;
        clk_dest = 1'b0;
        rst_n = 1'b0;
        #40;
        
        rst_n = 1'b1;
        $display("[TB] Reset liberado. Monitorando fluxo de dados...");

        // Simula por tempo suficiente para observar múltiplos ciclos do contador
        #600;

        $display("[TB] Simulacao finalizada.");
        $finish;
    end

    // LÓGICA DE MONITORAMENTO E DETECÇÃO DE PERDA (Scoreboard Estático)
    // Em Verilog 2001, usamos vetores fixos para registrar os estados (0 a 15)
    reg gerado_na_origem [0:15];
    reg [3:0] last_sync_out;
    
    integer total_gerado = 0;
    integer total_capturado = 0;
    integer total_perdido = 0;
    integer i;

    // Inicialização do array de monitoramento
    initial begin
        for (i = 0; i < 16; i = i + 1) begin
            gerado_na_origem[i] = 1'b0;
        end
    end

    // Captura o momento exato em que a origem gera um novo dado
    always @(posedge clk_src) begin
        if (rst_n) begin
            // Se o estado atual do contador ainda não foi marcado neste ciclo
            if (gerado_na_origem[dut.COUNTER_SYNC_module.count] == 1'b0) begin
                gerado_na_origem[dut.COUNTER_SYNC_module.count] = 1'b1;
                total_gerado = total_gerado + 1;
            end
        end
    end

    // Captura quando o destino consegue registrar o dado sincronizado
    always @(posedge clk_dest or negedge rst_n) begin
        if (!rst_n) begin
            last_sync_out <= 4'b0;
        end else begin
            last_sync_out <= dut.CDC_module.sync_out;
            
            // Detecta uma transição válida no registrador sincronizado final
            if (dut.CDC_module.sync_out != last_sync_out) begin
                $display("[CAPTURA] Destino amostrou o valor: %d no tempo %0t", dut.CDC_module.sync_out, $time);
                total_capturado = total_capturado + 1;
                
                // Limpa a marcação, pois o dado foi consumido pelo destino
                gerado_na_origem[dut.CDC_module.sync_out] = 1'b0;
            end
        end
    end

    // Varredura a cada ciclo de overflow do contador para computar perdas reais
    always @(posedge clk_src) begin
        if (rst_n && (dut.COUNTER_SYNC_module.count == 4'b1111)) begin
            #1; // Pequeno delay necessário para estabilização das amostras no TB
            
            // Varre o vetor: o que sobrou marcado como 1'b1 nunca foi lido pelo destino
            for (i = 0; i < 16; i = i + 1) begin
                if (gerado_na_origem[i] == 1'b1) begin
                    $display("[AVISO - PERDA] Valor %d gerado na origem NUNCA foi visto pelo destino.", i);
                    total_perdido = total_perdido + 1;
                    gerado_na_origem[i] = 1'b0; // Reseta para a próxima rodada
                end
            end
        end
    end

endmodule

CID-ADVANCED/CID-SD232/dump_fail.vcd
$date
	Sat Jun 27 03:00:20 2026
$end
$version
	Icarus Verilog
$end
$timescale
	1ps
$end
$scope module CDC_module_packet_loss_tb $end
$var wire 4 ! data_out [3:0] $end
$var reg 1 " clk_dest $end
$var reg 1 # clk_src $end
$var reg 4 $ last_sync_out [3:0] $end
$var reg 1 % rst_n $end
$var integer 32 & i [31:0] $end
$var integer 32 ' total_capturado [31:0] $end
$var integer 32 ( total_gerado [31:0] $end
$var integer 32 ) total_perdido [31:0] $end
$scope module dut $end
$var wire 1 " clk_dest $end
$var wire 1 # clk_src $end
$var wire 1 % rst_n $end
$var wire 4 * data_out [3:0] $end
$var wire 4 + count_cdc_out [3:0] $end
$var wire 4 , count_cdc_in [3:0] $end
$scope module CDC_module $end
$var wire 1 " clk_dest $end
$var wire 1 # clk_src $end
$var wire 1 % rst_n $end
$var wire 4 - sync_out [3:0] $end
$var wire 4 . count [3:0] $end
$var reg 4 / q1 [3:0] $end
$var reg 4 0 q2 [3:0] $end
$var reg 4 1 q_src [3:0] $end
$upscope $end
$scope module COMPARE_module $end
$var wire 1 " clk_dest $end
$var wire 4 2 count [3:0] $end
$var wire 1 % rst_n $end
$var reg 4 3 even_count [3:0] $end
$upscope $end
$scope module COUNTER_SYNC_module $end
$var wire 1 # clk_src $end
$var wire 1 % rst_n $end
$var reg 4 4 count [3:0] $end
$upscope $end
$upscope $end
$upscope $end
$enddefinitions $end
$comment Show the parameter values. $end
$dumpall
$end
#0
$dumpvars
b0 4
b0 3
b0 2
b0 1
b0 0
b0 /
b0 .
b0 -
b0 ,
b0 +
b0 *
b0 )
b0 (
b0 '
b10000 &
0%
bx $
0#
0"
b0 !
$end
#5000
1#
#10000
0#
#15000
1#
#17500
b0 $
1"
#20000
0#
#25000
1#
#30000
0#
#35000
1#
0"
#40000
0#
1%
#45000
b1 ,
b1 .
b1 4
b1 (
1#
#50000
0#
#52500
b1 !
b1 *
b1 3
1"
#55000
b10 ,
b10 .
b10 4
b1 1
b10 (
1#
#60000
0#
#65000
b10 1
b11 ,
b11 .
b11 4
b11 (
1#
#70000
0#
0"
#75000
b100 ,
b100 .
b100 4
b11 1
b100 (
1#
#80000
0#
#85000
b100 1
b101 ,
b101 .
b101 4
b101 (
1#
#87500
b10 !
b10 *
b10 3
b100 /
1"
#90000
0#
#95000
b110 ,
b110 .
b110 4
b101 1
b110 (
1#
#100000
0#
#105000
b110 1
b111 ,
b111 .
b111 4
b111 (
1#
0"
#110000
0#
#115000
b1000 ,
b1000 .
b1000 4
b111 1
b1000 (
1#
#120000
0#
#122500
b100 +
b100 -
b100 2
b100 0
b111 /
b11 !
b11 *
b11 3
1"
#125000
b1000 1
b1001 ,
b1001 .
b1001 4
b1001 (
1#
#130000
0#
#135000
b1010 ,
b1010 .
b1010 4
b1001 1
b1010 (
1#
#140000
0#
0"
#145000
b1010 1
b1011 ,
b1011 .
b1011 4
b1011 (
1#
#150000
0#
#155000
b1100 ,
b1100 .
b1100 4
b1011 1
b1100 (
1#
#157500
b111 +
b111 -
b111 2
b100 $
b100 !
b100 *
b100 3
b111 0
b1011 /
b1 '
1"
#160000
0#
#165000
b1100 1
b1101 ,
b1101 .
b1101 4
b1101 (
1#
#170000
0#
#175000
b1110 ,
b1110 .
b1110 4
b1101 1
b1110 (
1#
0"
#180000
0#
#185000
b1110 1
b1111 ,
b1111 .
b1111 4
b1111 (
1#
#190000
0#
#192500
b1011 +
b1011 -
b1011 2
b1011 0
b1110 /
b111 $
b10 '
1"
#195000
b0 ,
b0 .
b0 4
b1111 1
b10000 (
1#
#196000
b1110 )
b10000 &
#200000
0#
#205000
b0 1
b1 ,
b1 .
b1 4
b10001 (
1#
#210000
0#
0"
#215000
b10 ,
b10 .
b10 4
b1 1
b10010 (
1#
#220000
0#
#225000
b10 1
b11 ,
b11 .
b11 4
b10011 (
1#
#227500
b1110 +
b1110 -
b1110 2
b1011 $
b1110 0
b10 /
b11 '
1"
#230000
0#
#235000
b100 ,
b100 .
b100 4
b11 1
b10100 (
1#
#240000
0#
#245000
b100 1
b101 ,
b101 .
b101 4
b10101 (
1#
0"
#250000
0#
#255000
b110 ,
b110 .
b110 4
b101 1
b10110 (
1#
#260000
0#
#262500
b10 +
b10 -
b10 2
b10 0
b101 /
b101 !
b101 *
b101 3
b1110 $
b100 '
1"
#265000
b110 1
b111 ,
b111 .
b111 4
b10111 (
1#
#270000
0#
#275000
b1000 ,
b1000 .
b1000 4
b111 1
b11000 (
1#
#280000
0#
0"
#285000
b1000 1
b1001 ,
b1001 .
b1001 4
b11001 (
1#
#290000
0#
#295000
b1010 ,
b1010 .
b1010 4
b1001 1
b11010 (
1#
#297500
b101 +
b101 -
b101 2
b10 $
b110 !
b110 *
b110 3
b101 0
b1001 /
b101 '
1"
#300000
0#
#305000
b1010 1
b1011 ,
b1011 .
b1011 4
b11011 (
1#
#310000
0#
#315000
b1100 ,
b1100 .
b1100 4
b1011 1
b11100 (
1#
0"
#320000
0#
#325000
b1100 1
b1101 ,
b1101 .
b1101 4
b11101 (
1#
#330000
0#
#332500
b1001 +
b1001 -
b1001 2
b1001 0
b1100 /
b101 $
b110 '
1"
#335000
b1110 ,
b1110 .
b1110 4
b1101 1
b11110 (
1#
#340000
0#
#345000
b1110 1
b1111 ,
b1111 .
b1111 4
b11111 (
1#
#350000
0#
0"
#355000
b0 ,
b0 .
b0 4
b1111 1
b100000 (
1#
#356000
b11100 )
b10000 &
#360000
0#
#365000
b0 1
b1 ,
b1 .
b1 4
b100001 (
1#
#367500
b1100 +
b1100 -
b1100 2
b1001 $
b1100 0
b0 /
b111 '
1"
#370000
0#
#375000
b10 ,
b10 .
b10 4
b1 1
b100010 (
1#
#380000
0#
#385000
b10 1
b11 ,
b11 .
b11 4
b100011 (
1#
0"
#390000
0#
#395000
b100 ,
b100 .
b100 4
b11 1
b100100 (
1#
#400000
0#
#402500
b0 +
b0 -
b0 2
b0 0
b11 /
b111 !
b111 *
b111 3
b1100 $
b1000 '
1"
#405000
b100 1
b101 ,
b101 .
b101 4
b100101 (
1#
#410000
0#
#415000
b110 ,
b110 .
b110 4
b101 1
b100110 (
1#
#420000
0#
0"
#425000
b110 1
b111 ,
b111 .
b111 4
b100111 (
1#
#430000
0#
#435000
b1000 ,
b1000 .
b1000 4
b111 1
b101000 (
1#
#437500
b11 +
b11 -
b11 2
b0 $
b1000 !
b1000 *
b1000 3
b11 0
b111 /
b1001 '
1"
#440000
0#
#445000
b1000 1
b1001 ,
b1001 .
b1001 4
b101001 (
1#
#450000
0#
#455000
b1010 ,
b1010 .
b1010 4
b1001 1
b101010 (
1#
0"
#460000
0#
#465000
b1010 1
b1011 ,
b1011 .
b1011 4
b101011 (
1#
#470000
0#
#472500
b111 +
b111 -
b111 2
b111 0
b1010 /
b11 $
b1010 '
1"
#475000
b1100 ,
b1100 .
b1100 4
b1011 1
b101100 (
1#
#480000
0#
#485000
b1100 1
b1101 ,
b1101 .
b1101 4
b101101 (
1#
#490000
0#
0"
#495000
b1110 ,
b1110 .
b1110 4
b1101 1
b101110 (
1#
#500000
0#
#505000
b1110 1
b1111 ,
b1111 .
b1111 4
b101111 (
1#
#507500
b1010 +
b1010 -
b1010 2
b111 $
b1010 0
b1110 /
b1011 '
1"
#510000
0#
#515000
b0 ,
b0 .
b0 4
b1111 1
b110000 (
1#
#516000
b101001 )
b10000 &
#520000
0#
#525000
b0 1
b1 ,
b1 .
b1 4
b110001 (
1#
0"
#530000
0#
#535000
b10 ,
b10 .
b10 4
b1 1
b110010 (
1#
#540000
0#
#542500
b1110 +
b1110 -
b1110 2
b1110 0
b1 /
b1001 !
b1001 *
b1001 3
b1010 $
b1100 '
1"
#545000
b10 1
b11 ,
b11 .
b11 4
b110011 (
1#
#550000
0#
#555000
b100 ,
b100 .
b100 4
b11 1
b110100 (
1#
#560000
0#
0"
#565000
b100 1
b101 ,
b101 .
b101 4
b110101 (
1#
#570000
0#
#575000
b110 ,
b110 .
b110 4
b101 1
b110110 (
1#
#577500
b1 +
b1 -
b1 2
b1110 $
b1010 !
b1010 *
b1010 3
b1 0
b101 /
b1101 '
1"
#580000
0#
#585000
b110 1
b111 ,
b111 .
b111 4
b110111 (
1#
#590000
0#
#595000
b1000 ,
b1000 .
b1000 4
b111 1
b111000 (
1#
0"
#600000
0#
#605000
b1000 1
b1001 ,
b1001 .
b1001 4
b111001 (
1#
#610000
0#
#612500
b101 +
b101 -
b101 2
b101 0
b1000 /
b1 $
b1110 '
1"
#615000
b1010 ,
b1010 .
b1010 4
b1001 1
b111010 (
1#
#620000
0#
#625000
b1010 1
b1011 ,
b1011 .
b1011 4
b111011 (
1#
#630000
0#
0"
#635000
b1100 ,
b1100 .
b1100 4
b1011 1
b111100 (
1#
