CID-SD232/compare.v
`timescale 1 ns / 1 ps

module compare(
    input clk_dest,
    input rst_n,
    input       [3:0] count,
    output reg  [3:0] even_count
);

always @(posedge clk_dest or negedge rst_n) begin
    
	if (!rst_n) begin
		even_count <= 4'b0;
	end else
		if (count[0] == 0) even_count <= even_count + 1;
	end

endmodule

CID-SD232/cdc.v
`timescale 1 ns / 1 ps

module cdc (
    input clk_src,       
    input clk_dest,      
    input rst_n,
    input [3:0] count,   
    output [3:0] sync_out 
);

    reg [3:0] q_src; 
    reg [3:0] q1, q2; 

    always @(posedge clk_src or negedge rst_n) begin
        if (!rst_n) begin
            q_src <= 4'b0;
        end else begin
            q_src <= count;
        end
    end

    always @(posedge clk_dest or negedge rst_n) begin
        if (!rst_n) begin
            q1       <= 4'b0;
            q2       <= 4'b0;
        end else begin
            q1       <= q_src; 
            q2       <= q1;    
        end
    end
    
    assign sync_out = rst_n ? q2 : 4'b0;

endmodule

CID-ADVANCED/CID-SD232/contador_sincrono.v
`timescale 1 ns / 1 ps

module contador_sincrono (
    input clk_src,                       
    input rst_n,                                            
    output reg [3:0] count               
);

    always @(posedge clk_src or negedge rst_n) begin
        if (!rst_n) begin
            count <= 4'b0;
        end else begin
            if (count >= 4'b1111) begin
                count <= 4'b0;        // Retorna a zero ao atingir o máximo
            end else begin
                count <= count + 1'b1;     // Incrementa a contagem
            end
        end
    end

endmodule

CID-ADVANCED/CID-SD232/top.v
`include "contador_sincrono.v"
`include "cdc.v"
`include "compare.v"

`timescale 1 ns / 1 ps

module top (
    
    input clk_dest, clk_src,
    input rst_n,
    output  [3:0] data_out
    
);
	wire [3:0] count_cdc_in, count_cdc_out;

	contador_sincrono COUNTER_SYNC_module (  
		.clk_src(clk_src),
		.rst_n (rst_n),
		.count (count_cdc_in)
	);

	cdc CDC_module (   
		.clk_dest(clk_dest),
		.clk_src (clk_src),
		.rst_n(rst_n),
		.count(count_cdc_in),
		.sync_out(count_cdc_out)
	);

	compare COMPARE_module ( 
		.clk_dest(clk_dest),
		.rst_n (rst_n),
		.count(count_cdc_out),
		.even_count(data_out)
	);

endmodule

CID-ADVANCED/CID-SD232/top_tb.v
`include "top.v"
`timescale 1 ns / 1 ps

module top_tb ();

	// Declaração de sinais
	reg clk_src;
	reg clk_dest;
	reg rst_n;
	wire [3:0] data_out;

	// Instanciação do DUT (Device Under Test)
	top dut (
		.clk_dest(clk_dest),
		.clk_src(clk_src),
		.rst_n(rst_n),
		.data_out(data_out)
	);

	// 250 MHz
	always #( (1.0/250.0) * 10**3) clk_src = ~clk_src;
	// 491.52 MHz
	always #( (1.0/491.52) * 10**3) clk_dest = ~clk_dest;

	// Monitoramento dos Sinais (Scoreboard Simples)
	initial begin
		// Format: scale to ns (-9, 2 decimal digits, min width of 10 chars;
		$timeformat( -9, 1, "", 10);
		$dumpfile("dump.vcd");
		$dumpvars(0, top_tb);
		$display("Tempo	(ns)	|rst_n	|Count_Src	|Dest_Sync	|Even_Count	|");
		$monitor("|%0t		|%b	|%d		|%d		|%d		|", 
		$realtime, rst_n, dut.COUNTER_SYNC_module.count, dut.CDC_module.sync_out, data_out);
	
	end

	// Geração de Estímulos e Reset
	initial begin
		// Reset
		clk_src	 = 1'b0;
		clk_dest = 1'b0;
		rst_n 	 = 1'b0;

		#15;
		rst_n = 1'b1;

		// Contador: reiniciar (overflow)
		#200;

		$finish;
	end

endmodule

CID-ADVANCED/CID-SD232/dump.vcd
$date
	Sat Jun 27 03:12:10 2026
$end
$version
	Icarus Verilog
$end
$timescale
	1ps
$end
$scope module top_tb $end
$var wire 4 ! data_out [3:0] $end
$var reg 1 " clk_dest $end
$var reg 1 # clk_src $end
$var reg 1 $ rst_n $end
$scope module dut $end
$var wire 1 " clk_dest $end
$var wire 1 # clk_src $end
$var wire 1 $ rst_n $end
$var wire 4 % data_out [3:0] $end
$var wire 4 & count_cdc_out [3:0] $end
$var wire 4 ' count_cdc_in [3:0] $end
$scope module CDC_module $end
$var wire 1 " clk_dest $end
$var wire 1 # clk_src $end
$var wire 1 $ rst_n $end
$var wire 4 ( sync_out [3:0] $end
$var wire 4 ) count [3:0] $end
$var reg 4 * q1 [3:0] $end
$var reg 4 + q2 [3:0] $end
$var reg 4 , q_src [3:0] $end
$upscope $end
$scope module COMPARE_module $end
$var wire 1 " clk_dest $end
$var wire 4 - count [3:0] $end
$var wire 1 $ rst_n $end
$var reg 4 . even_count [3:0] $end
$upscope $end
$scope module COUNTER_SYNC_module $end
$var wire 1 # clk_src $end
$var wire 1 $ rst_n $end
$var reg 4 / count [3:0] $end
$upscope $end
$upscope $end
$upscope $end
$enddefinitions $end
$comment Show the parameter values. $end
$dumpall
$end
#0
$dumpvars
b0 /
b0 .
b0 -
b0 ,
b0 +
b0 *
b0 )
b0 (
b0 '
b0 &
b0 %
0$
0#
0"
b0 !
$end
#2035
1"
#4000
1#
#4070
0"
#6105
1"
#8000
0#
#8140
0"
#10175
1"
#12000
1#
#12210
0"
#14245
1"
#15000
1$
#16000
0#
#16280
0"
#18315
b1 !
b1 %
b1 .
1"
#20000
b1 '
b1 )
b1 /
1#
#20350
0"
#22385
b10 !
b10 %
b10 .
1"
#24000
0#
#24420
0"
#26455
b11 !
b11 %
b11 .
1"
#28000
b10 '
b10 )
b10 /
b1 ,
1#
#28490
0"
#30525
b1 *
b100 !
b100 %
b100 .
1"
#32000
0#
#32560
0"
#34595
b1 &
b1 (
b1 -
b101 !
b101 %
b101 .
b1 +
1"
#36000
b10 ,
b11 '
b11 )
b11 /
1#
#36630
0"
#38665
b10 *
1"
#40000
0#
#40700
0"
#42735
b10 &
b10 (
b10 -
b10 +
1"
#44000
b100 '
b100 )
b100 /
b11 ,
1#
#44770
0"
#46805
b11 *
b110 !
b110 %
b110 .
1"
#48000
0#
#48840
0"
#50875
b11 &
b11 (
b11 -
b111 !
b111 %
b111 .
b11 +
1"
#52000
b100 ,
b101 '
b101 )
b101 /
1#
#52910
0"
#54945
b100 *
1"
#56000
0#
#56980
0"
#59015
b100 &
b100 (
b100 -
b100 +
1"
#60000
b110 '
b110 )
b110 /
b101 ,
1#
#61050
0"
#63085
b101 *
b1000 !
b1000 %
b1000 .
1"
#64000
0#
#65120
0"
#67155
b101 &
b101 (
b101 -
b1001 !
b1001 %
b1001 .
b101 +
1"
#68000
b110 ,
b111 '
b111 )
b111 /
1#
#69190
0"
#71225
b110 *
1"
#72000
0#
#73260
0"
#75295
b110 &
b110 (
b110 -
b110 +
1"
#76000
b1000 '
b1000 )
b1000 /
b111 ,
1#
#77330
0"
#79365
b111 *
b1010 !
b1010 %
b1010 .
1"
#80000
0#
#81400
0"
#83435
b111 &
b111 (
b111 -
b1011 !
b1011 %
b1011 .
b111 +
1"
#84000
b1000 ,
b1001 '
b1001 )
b1001 /
1#
#85470
0"
#87505
b1000 *
1"
#88000
0#
#89540
0"
#91575
b1000 &
b1000 (
b1000 -
b1000 +
1"
#92000
b1010 '
b1010 )
b1010 /
b1001 ,
1#
#93610
0"
#95645
b1001 *
b1100 !
b1100 %
b1100 .
1"
#96000
0#
#97680
0"
#99715
b1001 &
b1001 (
b1001 -
b1101 !
b1101 %
b1101 .
b1001 +
1"
#100000
b1010 ,
b1011 '
b1011 )
b1011 /
1#
#101750
0"
#103785
b1010 *
1"
#104000
0#
#105820
0"
#107855
b1010 &
b1010 (
b1010 -
b1010 +
1"
#108000
b1100 '
b1100 )
b1100 /
b1011 ,
1#
#109890
0"
#111925
b1011 *
b1110 !
b1110 %
b1110 .
1"
#112000
0#
#113960
0"
#115995
b1011 &
b1011 (
b1011 -
b1111 !
b1111 %
b1111 .
b1011 +
1"
#116000
b1100 ,
b1101 '
b1101 )
b1101 /
1#
#118030
0"
#120000
0#
#120065
b1100 *
1"
#122100
0"
#124000
b1110 '
b1110 )
b1110 /
b1101 ,
1#
#124135
b1100 &
b1100 (
b1100 -
b1100 +
b1101 *
1"
#126170
0"
#128000
0#
#128205
b1101 &
b1101 (
b1101 -
b1101 +
b0 !
b0 %
b0 .
1"
#130240
0"
#132000
b1110 ,
b1111 '
b1111 )
b1111 /
1#
#132275
b1110 *
1"
#134310
0"
#136000
0#
#136345
b1110 &
b1110 (
b1110 -
b1110 +
1"
#138380
0"
#140000
b0 '
b0 )
b0 /
b1111 ,
1#
#140415
b1 !
b1 %
b1 .
b1111 *
1"
#142450
0"
#144000
0#
#144485
b1111 &
b1111 (
b1111 -
b1111 +
b10 !
b10 %
b10 .
1"
#146520
0"
#148000
b0 ,
b1 '
b1 )
b1 /
1#
#148555
b0 *
1"
#150590
0"
#152000
0#
#152625
b0 &
b0 (
b0 -
b0 +
1"
#154660
0"
#156000
b10 '
b10 )
b10 /
b1 ,
1#
#156695
b11 !
b11 %
b11 .
b1 *
1"
#158730
0"
#160000
0#
#160765
b1 &
b1 (
b1 -
b1 +
b100 !
b100 %
b100 .
1"
#162800
0"
#164000
b10 ,
b11 '
b11 )
b11 /
1#
#164835
b10 *
1"
#166870
0"
#168000
0#
#168905
b10 &
b10 (
b10 -
b10 +
1"
#170940
0"
#172000
b100 '
b100 )
b100 /
b11 ,
1#
#172975
b101 !
b101 %
b101 .
b11 *
1"
#175010
0"
#176000
0#
#177045
b11 &
b11 (
b11 -
b11 +
b110 !
b110 %
b110 .
1"
#179080
0"
#180000
b100 ,
b101 '
b101 )
b101 /
1#
#181115
b100 *
1"
#183150
0"
#184000
0#
#185185
b100 &
b100 (
b100 -
b100 +
1"
#187220
0"
#188000
b110 '
b110 )
b110 /
b101 ,
1#
#189255
b111 !
b111 %
b111 .
b101 *
1"
#191290
0"
#192000
0#
#193325
b101 &
b101 (
b101 -
b101 +
b1000 !
b1000 %
b1000 .
1"
#195360
0"
#196000
b110 ,
b111 '
b111 )
b111 /
1#
#197395
b110 *
1"
#199430
0"
#200000
0#
#201465
b110 &
b110 (
b110 -
b110 +
1"
#203500
0"
#204000
b1000 '
b1000 )
b1000 /
b111 ,
1#
#205535
b1001 !
b1001 %
b1001 .
b111 *
1"
#207570
0"
#208000
0#
#209605
b111 &
b111 (
b111 -
b111 +
b1010 !
b1010 %
b1010 .
1"
#211640
0"
#212000
b1000 ,
b1001 '
b1001 )
b1001 /
1#
#213675
b1000 *
1"
